pyspark_assert/__init__.py
pyspark_assert/_assertions.py
pyspark_assert/_testing.py
pyspark_assert/_utils.py
pyspark_assert/_wrappers.py
pyspark_assert-0.1.0.dist-info/LICENSE
pyspark_assert-0.1.0.dist-info/METADATA
pyspark_assert-0.1.0.dist-info/WHEEL
pyspark_assert-0.1.0.dist-info/RECORD
