Metadata-Version: 2.1
Name: pyspark-assert
Version: 0.1.0
Summary: Simple unit testing library for PySpark.
Author: Soy-yo
Requires-Python: >=3.7,<4.0
Classifier: Programming Language :: Python :: 3
Classifier: Programming Language :: Python :: 3.7
Classifier: Programming Language :: Python :: 3.8
Classifier: Programming Language :: Python :: 3.9
Classifier: Programming Language :: Python :: 3.10
Classifier: Programming Language :: Python :: 3.11
